Patrick_Liang_Portfolio/School_Work/ece474/hw4/controller.sv
module controller(
    input logic [2:0] req,
    input logic [2:0] done,
    input logic reset, clk,
    output logic [3:0] mstate,
    output logic [1:0] accmodule
);
logic m2_m3_alt; //M2 is 0, M3 is 1
logic [1:0] clk_counter;
logic interrupt;

enum logic [3:0] {
    IDLE = 4'b0001,
    M1   = 4'b0010,
    M2   = 4'b0100,
    M3   = 4'b1000
} current_state, next_state;

// output logic
always_comb begin
    case(current_state)
        IDLE: accmodule = 2'b00;
        M1: accmodule = 2'b01;
        M2: accmodule = 2'b10;
        M3: accmodule = 2'b11;
    endcase
end

assign mstate = current_state;

// internal logic
always_ff @ (posedge clk or posedge reset) begin
    if(reset) begin
        m2_m3_alt <= 1'b0;
        clk_counter <= 2'b00;
        interrupt <= 1'b0;
    end
    else begin
        // M2 M3 alternating logic
        if(req[1] & req[2] & (next_state == M2 | next_state == M3))
            m2_m3_alt <= ~m2_m3_alt;
        
        // interrupt logic
        if((current_state == M2 | current_state == M3) & next_state == M1)
            interrupt <= 1'b1;
        if(current_state == M1 & next_state != M1)
            interrupt <= 1'b0;

        // clk_counter logic
        if(current_state != next_state)
            clk_counter <= 2'b00;
        else
            clk_counter <= clk_counter + 1;

    end
end

// current_state logic
always_ff @ (posedge clk or posedge reset) begin
    if(reset)
        current_state <= IDLE;
    else
        current_state <= next_state;
end

// next_state logic
always_comb begin
    case(current_state)
        IDLE: begin
            if(req[0]) 
                next_state = M1;
            else if(req[1] & req[2])
                next_state = m2_m3_alt ? M3 : M2;
            else if(req[1])
                next_state = M2;
            else if(req[2])
                next_state = M3;
            else
                next_state = IDLE;
        end
        M1: begin
            if((clk_counter == 2'b1 & interrupt) | done[0]) begin
                if(req[1] & req[2])
                    next_state = m2_m3_alt ? M3 : M2;
                else if(req[1])
                    next_state = M2;
                else if(req[2])
                    next_state = M3;
                else
                    next_state = IDLE;
            end
            else
                next_state = M1;
        end
        M2: begin
            if(req[0])
                next_state = M1;
            else if(clk_counter == 2'b1 | done[1]) begin
                if(req[0]) 
                    next_state = M1;
                else if(req[2])
                    next_state = M3;
                else
                    next_state = IDLE;
            end
            else
                next_state = M2;
        end
        M3: begin
            if(req[0])
                next_state = M1;
            else if(clk_counter == 2'b1 | done[2]) begin
                if(req[0]) 
                    next_state = M1;
                else if(req[1])
                    next_state = M2;
                else
                    next_state = IDLE;
            end
            else
                next_state = M3;
        end
    endcase
end


endmodule

Patrick_Liang_Portfolio/School_Work/ece474/hw4/tb_controller.sv
`timescale 1ns/1ns
// Example testbench for homework 4 memory controller.
// Author: Richard Yu
// Date: 05/02/2022

module tb_controller ();

parameter MONE = 0, MTWO = 1, MTHREE = 2;

logic [2:0] req;
logic [2:0] done;
logic clk, rst;  // Input signals to the DUT.

logic [3:0] mstate;
logic [1:0] accmodule;

controller iDUT(.req(req), .done(done), .reset(rst), .clk(clk), .mstate(mstate), .accmodule(accmodule));



initial begin

clk = 0;
rst = 1;
req[MONE] = 0;
req[MTWO] = 0;
req[MTHREE] = 0;
done[MONE] = 0;
done[MTWO] = 0;
done[MTHREE] = 0;

# 14 rst = 0;

// Module 1 requests, module 2 tries to interupts but fails.
# 2 req[MONE] = 1;
# 10 req[MONE] = 0;

# 20 req[MTWO] = 1;
# 10 req[MTWO] = 0;

# 5 done[MONE] = 1;
# 5 done[MONE] = 0;

// Module 2 requests, module 1 to interupts.
# 20 req[MTWO] = 1;
# 10 req[MTWO] = 0;

# 10 req[MONE] = 1;
# 10 req[MONE] = 0;

# 35 done[MONE] = 1;
# 5  done[MONE] = 0;

// Module 3 requests, module 1 to interupts.
# 20 req[MTHREE] = 1;
# 10 req[MTHREE] = 0;

# 10 req[MONE] = 1;
# 10 req[MONE] = 0;

# 35 done[MONE] = 1;
# 5  done[MONE] = 0;

// Module 2 and module 3 both request, access given to module 2.
# 20 req[MTHREE] = 1;
	 req[MTWO] = 1;
# 10 req[MTHREE] = 0;
	 req[MTWO] = 0;

# 15 done[MTWO] = 1;
# 5 done[MTWO] = 0;

// Module 2 and module 3 both request again, access given to module 3.
# 10 req[MTHREE] = 1;
	 req[MTWO] = 1;
# 10 req[MTHREE] = 0;
	 req[MTWO] = 0;

# 15 done[MTWO] = 1;
# 5 done[MTWO] = 0;

// Module 2 and module 3 both request again, access given to module 2.
# 10 req[MTHREE] = 1;
	 req[MTWO] = 1;
# 10 req[MTHREE] = 0;
	 req[MTWO] = 0;

# 15 done[MTWO] = 1;
# 5 done[MTWO] = 0;

// Module 2 and module 3 both request again, access given to module 3.
# 10 req[MTHREE] = 1;
	 req[MTWO] = 1;
# 10 req[MTHREE] = 0;
	 req[MTWO] = 0;

# 15 done[MTWO] = 1;
# 5 done[MTWO] = 0;

// Module 2 and module 3 both request again, access given to module 2.
# 10 req[MTHREE] = 1;
	 req[MTWO] = 1;
# 10 req[MTHREE] = 0;
	 req[MTWO] = 0;

# 15 done[MTWO] = 1;
# 5 done[MTWO] = 0;

// Module 1 to 2 to 3 back to back
# 10 req[MONE] = 1;
# 10 req[MONE] = 0;
	 req[MTWO] = 1;

# 5 done[MONE] = 1;

# 5 done[MONE] = 0;
	req[MTWO] = 0;

# 10 req[MTHREE] = 1;

# 5 done[MTWO] = 1;

# 5 done[MTWO] = 0;
	req[MTHREE] = 0;

# 20
# 20 $dumpflush;
$stop;


end

initial begin
$dumpfile("test.vcd");
$dumpvars(1, tb_controller);

end


always
	#5 clk = ~clk;

endmodule

Patrick_Liang_Portfolio/School_Work/ece474/hw4/test.vcd
$date
	Tue May 16 17:09:22 2023
$end
$version
	ModelSim Version 2021.2
$end
$timescale
	1ns
$end

$scope module tb_controller $end
$var parameter 32 ! MONE $end
$var parameter 32 " MTWO $end
$var parameter 32 # MTHREE $end
$var reg 3 $ req [2:0] $end
$var reg 3 % done [2:0] $end
$var reg 1 & clk $end
$var reg 1 ' rst $end
$var reg 4 ( mstate [3:0] $end
$var reg 2 ) accmodule [1:0] $end
$upscope $end
$enddefinitions $end
#0
$dumpvars
b0 $
b0 %
0&
1'
b1 (
b0 )
b0 !
b1 "
b10 #
$end
#5
1&
#10
0&
#14
0'
#15
1&
#16
b1 $
#20
0&
#25
1&
b10 (
b1 )
#26
b0 $
#30
0&
#35
1&
#40
0&
#45
1&
#46
b10 $
#50
0&
#55
1&
#56
b0 $
#60
0&
#61
b1 %
#65
1&
b1 (
b0 )
#66
b0 %
#70
0&
#75
1&
#80
0&
#85
1&
#86
b10 $
#90
0&
#95
1&
b100 (
b10 )
#96
b0 $
#100
0&
#105
1&
#106
b1 $
#110
0&
#115
1&
b10 (
b1 )
#116
b0 $
#120
0&
#125
1&
#130
0&
#135
1&
b1 (
b0 )
#140
0&
#145
1&
#150
0&
#151
b1 %
#155
1&
#156
b0 %
#160
0&
#165
1&
#170
0&
#175
1&
#176
b100 $
#180
0&
#185
1&
b1000 (
b11 )
#186
b0 $
#190
0&
#195
1&
#196
b1 $
#200
0&
#205
1&
b10 (
b1 )
#206
b0 $
#210
0&
#215
1&
#220
0&
#225
1&
b1 (
b0 )
#230
0&
#235
1&
#240
0&
#241
b1 %
#245
1&
#246
b0 %
#250
0&
#255
1&
#260
0&
#265
1&
#266
b100 $
b110 $
#270
0&
#275
1&
b100 (
b10 )
#276
b10 $
b0 $
#280
0&
#285
1&
#290
0&
#291
b10 %
#295
1&
b1 (
b0 )
#296
b0 %
#300
0&
#305
1&
#306
b100 $
b110 $
#310
0&
#315
1&
b1000 (
b11 )
#316
b10 $
b0 $
#320
0&
#325
1&
#330
0&
#331
b10 %
#335
1&
b1 (
b0 )
#336
b0 %
#340
0&
#345
1&
#346
b100 $
b110 $
#350
0&
#355
1&
b100 (
b10 )
#356
b10 $
b0 $
#360
0&
#365
1&
#370
0&
#371
b10 %
#375
1&
b1 (
b0 )
#376
b0 %
#380
0&
#385
1&
#386
b100 $
b110 $
#390
0&
#395
1&
b1000 (
b11 )
#396
b10 $
b0 $
#400
0&
#405
1&
#410
0&
#411
b10 %
#415
1&
b1 (
b0 )
#416
b0 %
#420
0&
#425
1&
#426
b100 $
b110 $
#430
0&
#435
1&
b100 (
b10 )
#436
b10 $
b0 $
#440
0&
#445
1&
#450
0&
#451
b10 %
#455
1&
b1 (
b0 )
#456
b0 %
#460
0&
#465
1&
#466
b1 $
#470
0&
#475
1&
b10 (
b1 )
#476
b0 $
b10 $
#480
0&
#481
b1 %
#485
1&
b100 (
b10 )
#486
b0 %
b0 $
#490
0&
#495
1&
#496
b100 $
#500
0&
#501
b10 %
#505
1&
b1000 (
b11 )
#506
b0 %
b0 $
#510
0&
#515
1&
#520
0&
#525
1&
b1 (
b0 )
